{
  "crs": {
    "source": "CGCS2000",
    "sourceEpsg": 4547,
    "target": "WGS84",
    "targetEpsg": 4326
  },
  "segments": [
    {
      "id": "1d96e130f8944f2dbdb1e5458b4d78f5",
      "name": "风机中心点-1d96e130f8944f2dbdb1e5458b4d78f5",
      "type": 0,
      "layer": "风机中心点",
      "points": [
        {
          "lon": 121.59397126,
          "lat": 32.67833588,
          "alt": 0.0,
          "raw": {
            "x": 649508.019,
            "y": 3618198.009,
            "z": 0.0
          }
        }
      ]
    },
    {
      "id": "c3fdf6e0419f4d30841d2fe3c7198c72",
      "name": "风机中心点-c3fdf6e0419f4d30841d2fe3c7198c72",
      "type": 0,
      "layer": "风机中心点",
      "points": [
        {
          "lon": 121.59855225,
          "lat": 32.67978846,
          "alt": 0.0,
          "raw": {
            "x": 649935.3161,
            "y": 3618365.59,
            "z": 0.0
          }
        }
      ]
    },
    {
      "id": "9814344a6fd145c28b8d0d36fb58aeb3",
      "name": "风机中心点-9814344a6fd145c28b8d0d36fb58aeb3",
      "type": 0,
      "layer": "风机中心点",
      "points": [
        {
          "lon": 121.60313354,
          "lat": 32.68124087,
          "alt": 0.0,
          "raw": {
            "x": 650362.628,
            "y": 3618533.172,
            "z": 0.0
          }
        }
      ]
    },
    {
      "id": "4b362b6fb546443d869ab4a9b888fa65",
      "name": "风机中心点-4b362b6fb546443d869ab4a9b888fa65",
      "type": 0,
      "layer": "风机中心点",
      "points": [
        {
          "lon": 121.58022891,
          "lat": 32.67397709,
          "alt": 0.0,
          "raw": {
            "x": 648226.105,
            "y": 3617695.262,
            "z": 0.0
          }
        }
      ]
    },
    {
      "id": "69bd281865f94a1f9e2740f7e15c5cd4",
      "name": "风机中心点-69bd281865f94a1f9e2740f7e15c5cd4",
      "type": 0,
      "layer": "风机中心点",
      "points": [
        {
          "lon": 121.58480956,
          "lat": 32.67543019,
          "alt": 0.0,
          "raw": {
            "x": 648653.41,
            "y": 3617862.844,
            "z": 0.0
          }
        }
      ]
    },
    {
      "id": "07a24d8477f141fab7dde78f6be24b47",
      "name": "风机中心点-07a24d8477f141fab7dde78f6be24b47",
      "type": 0,
      "layer": "风机中心点",
      "points": [
        {
          "lon": 121.58939033,
          "lat": 32.6768831,
          "alt": 0.0,
          "raw": {
            "x": 649080.714,
            "y": 3618030.424,
            "z": 0.0
          }
        }
      ]
    },
    {
      "id": "b917bfe255fd455d905010e8514fbf09",
      "name": "风机中心点-b917bfe255fd455d905010e8514fbf09",
      "type": 0,
      "layer": "风机中心点",
      "points": [
        {
          "lon": 121.6214597,
          "lat": 32.68704878,
          "alt": 0.0,
          "raw": {
            "x": 652071.837,
            "y": 3619203.498,
            "z": 0.0
          }
        }
      ]
    },
    {
      "id": "4f771167783f41688de31dfb104ed8db",
      "name": "风机中心点-4f771167783f41688de31dfb104ed8db",
      "type": 0,
      "layer": "风机中心点",
      "points": [
        {
          "lon": 121.62604171,
          "lat": 32.68850033,
          "alt": 0.0,
          "raw": {
            "x": 652499.15,
            "y": 3619371.08,
            "z": 0.0
          }
        }
      ]
    },
    {
      "id": "68b94adc88694b7e869e52a7c42c8d08",
      "name": "风机中心点-68b94adc88694b7e869e52a7c42c8d08",
      "type": 0,
      "layer": "风机中心点",
      "points": [
        {
          "lon": 121.63062368,
          "lat": 32.68995174,
          "alt": 0.0,
          "raw": {
            "x": 652926.4464,
            "y": 3619538.665,
            "z": 0.0
          }
        }
      ]
    },
    {
      "id": "527a83023d0f4835879b8b79dbbd3e53",
      "name": "风机中心点-527a83023d0f4835879b8b79dbbd3e53",
      "type": 0,
      "layer": "风机中心点",
      "points": [
        {
          "lon": 121.60771489,
          "lat": 32.68269312,
          "alt": 0.0,
          "raw": {
            "x": 650789.933,
            "y": 3618700.755,
            "z": 0.0
          }
        }
      ]
    },
    {
      "id": "21b2ad2352ae4f6d8e3b2ba8aeac579c",
      "name": "风机中心点-21b2ad2352ae4f6d8e3b2ba8aeac579c",
      "type": 0,
      "layer": "风机中心点",
      "points": [
        {
          "lon": 121.61229631,
          "lat": 32.68414519,
          "alt": 0.0,
          "raw": {
            "x": 651217.2301,
            "y": 3618868.337,
            "z": 0.0
          }
        }
      ]
    },
    {
      "id": "97c64293583c4b0db39f65c9de30c0f8",
      "name": "风机中心点-97c64293583c4b0db39f65c9de30c0f8",
      "type": 0,
      "layer": "风机中心点",
      "points": [
        {
          "lon": 121.6168781,
          "lat": 32.68559708,
          "alt": 0.0,
          "raw": {
            "x": 651644.5495,
            "y": 3619035.919,
            "z": 0.0
          }
        }
      ]
    },
    {
      "id": "06f06691cbfd4341be1f73107f24bcf3",
      "name": "风机中心点-06f06691cbfd4341be1f73107f24bcf3",
      "type": 0,
      "layer": "风机中心点",
      "points": [
        {
          "lon": 121.57564842,
          "lat": 32.67252381,
          "alt": 0.0,
          "raw": {
            "x": 647798.801,
            "y": 3617527.68,
            "z": 0.0
          }
        }
      ]
    },
    {
      "id": "66a34c4f6d384d96abb03cb6ee4d3c18",
      "name": "风机中心点-66a34c4f6d384d96abb03cb6ee4d3c18",
      "type": 0,
      "layer": "风机中心点",
      "points": [
        {
          "lon": 121.53443033,
          "lat": 32.6594366,
          "alt": 0.0,
          "raw": {
            "x": 643953.06,
            "y": 3616019.441,
            "z": 0.0
          }
        }
      ]
    },
    {
      "id": "fa3b5f302c4e4a56aa95ca41ad76d1fb",
      "name": "风机中心点-fa3b5f302c4e4a56aa95ca41ad76d1fb",
      "type": 0,
      "layer": "风机中心点",
      "points": [
        {
          "lon": 121.53900955,
          "lat": 32.66089142,
          "alt": 0.0,
          "raw": {
            "x": 644380.3642,
            "y": 3616187.023,
            "z": 0.0
          }
        }
      ]
    },
    {
      "id": "c762091fff7049cd877a20d7d798f0aa",
      "name": "风机中心点-c762091fff7049cd877a20d7d798f0aa",
      "type": 0,
      "layer": "风机中心点",
      "points": [
        {
          "lon": 121.54358891,
          "lat": 32.66234607,
          "alt": 0.0,
          "raw": {
            "x": 644807.669,
            "y": 3616354.605,
            "z": 0.0
          }
        }
      ]
    },
    {
      "id": "5b9ed0a67ec3422cbb9d2ac07b2a94b8",
      "name": "风机中心点-5b9ed0a67ec3422cbb9d2ac07b2a94b8",
      "type": 0,
      "layer": "风机中心点",
      "points": [
        {
          "lon": 121.52069353,
          "lat": 32.6550711,
          "alt": 0.0,
          "raw": {
            "x": 642671.146,
            "y": 3615516.694,
            "z": 0.0
          }
        }
      ]
    },
    {
      "id": "59e558985cf2475fae3ff08892260602",
      "name": "风机中心点-59e558985cf2475fae3ff08892260602",
      "type": 0,
      "layer": "风机中心点",
      "points": [
        {
          "lon": 121.52527233,
          "lat": 32.65652643,
          "alt": 0.0,
          "raw": {
            "x": 643098.451,
            "y": 3615684.276,
            "z": 0.0
          }
        }
      ]
    },
    {
      "id": "7dd04440deea4a8fa76996f1fa07b89f",
      "name": "风机中心点-7dd04440deea4a8fa76996f1fa07b89f",
      "type": 0,
      "layer": "风机中心点",
      "points": [
        {
          "lon": 121.52985124,
          "lat": 32.65798049,
          "alt": 0.0,
          "raw": {
            "x": 643525.756,
            "y": 3615851.735,
            "z": 0.0
          }
        }
      ]
    },
    {
      "id": "1720bd17256f456b89918deb48828270",
      "name": "风机中心点-1720bd17256f456b89918deb48828270",
      "type": 0,
      "layer": "风机中心点",
      "points": [
        {
          "lon": 121.56190777,
          "lat": 32.66816295,
          "alt": 0.0,
          "raw": {
            "x": 646516.887,
            "y": 3617024.933,
            "z": 0.0
          }
        }
      ]
    },
    {
      "id": "07ba14fd0d164eb4b4fb08f0a7241c7d",
      "name": "风机中心点-07ba14fd0d164eb4b4fb08f0a7241c7d",
      "type": 0,
      "layer": "风机中心点",
      "points": [
        {
          "lon": 121.56648785,
          "lat": 32.66961675,
          "alt": 0.0,
          "raw": {
            "x": 646944.192,
            "y": 3617192.516,
            "z": 0.0
          }
        }
      ]
    },
    {
      "id": "d098c7bfe16b43ad9e72a9b1d4b09bed",
      "name": "风机中心点-d098c7bfe16b43ad9e72a9b1d4b09bed",
      "type": 0,
      "layer": "风机中心点",
      "points": [
        {
          "lon": 121.57106806,
          "lat": 32.67107037,
          "alt": 0.0,
          "raw": {
            "x": 647371.496,
            "y": 3617360.098,
            "z": 0.0
          }
        }
      ]
    },
    {
      "id": "7d04eff3f2d54ce6a17603057ab6a800",
      "name": "风机中心点-7d04eff3f2d54ce6a17603057ab6a800",
      "type": 0,
      "layer": "风机中心点",
      "points": [
        {
          "lon": 121.54816842,
          "lat": 32.66380054,
          "alt": 0.0,
          "raw": {
            "x": 645234.974,
            "y": 3616522.186,
            "z": 0.0
          }
        }
      ]
    },
    {
      "id": "7f94b71793e64d2e9ebd90341fc456cb",
      "name": "风机中心点-7f94b71793e64d2e9ebd90341fc456cb",
      "type": 0,
      "layer": "风机中心点",
      "points": [
        {
          "lon": 121.55274806,
          "lat": 32.66525486,
          "alt": 0.0,
          "raw": {
            "x": 645662.278,
            "y": 3616689.769,
            "z": 0.0
          }
        }
      ]
    },
    {
      "id": "4e5286a91e57499b871f7f76e8ae1273",
      "name": "风机中心点-4e5286a91e57499b871f7f76e8ae1273",
      "type": 0,
      "layer": "风机中心点",
      "points": [
        {
          "lon": 121.55732785,
          "lat": 32.66670899,
          "alt": 0.0,
          "raw": {
            "x": 646089.583,
            "y": 3616857.351,
            "z": 0.0
          }
        }
      ]
    },
    {
      "id": "2bd4349a12114bfa9228d0f4b7e5eaf8",
      "name": "风机中心点-2bd4349a12114bfa9228d0f4b7e5eaf8",
      "type": 0,
      "layer": "风机中心点",
      "points": [
        {
          "lon": 121.57819835,
          "lat": 32.65820749,
          "alt": 0.0,
          "raw": {
            "x": 648061.628,
            "y": 3615943.322,
            "z": 0.0
          }
        }
      ]
    },
    {
      "id": "2c1ed476633d4a0381611a49a235e7d5",
      "name": "风机中心点-2c1ed476633d4a0381611a49a235e7d5",
      "type": 0,
      "layer": "风机中心点",
      "points": [
        {
          "lon": 121.57234955,
          "lat": 32.65652096,
          "alt": 0.0,
          "raw": {
            "x": 647515.6248,
            "y": 3615748.115,
            "z": 0.0
          }
        }
      ]
    },
    {
      "id": "78944d62fa9b4c7096f1ab38db02d0a6",
      "name": "风机中心点-78944d62fa9b4c7096f1ab38db02d0a6",
      "type": 0,
      "layer": "风机中心点",
      "points": [
        {
          "lon": 121.56650094,
          "lat": 32.65483407,
          "alt": 0.0,
          "raw": {
            "x": 646969.6201,
            "y": 3615552.9,
            "z": 0.0
          }
        }
      ]
    },
    {
      "id": "22c778a8ac824b0bb380c7f63ce37e6d",
      "name": "风机中心点-22c778a8ac824b0bb380c7f63ce37e6d",
      "type": 0,
      "layer": "风机中心点",
      "points": [
        {
          "lon": 121.59574595,
          "lat": 32.6632654,
          "alt": 0.0,
          "raw": {
            "x": 649699.633,
            "y": 3616528.943,
            "z": 0.0
          }
        }
      ]
    },
    {
      "id": "f26f24415e2c430dbdbc3f4d0abecc1a",
      "name": "风机中心点-f26f24415e2c430dbdbc3f4d0abecc1a",
      "type": 0,
      "layer": "风机中心点",
      "points": [
        {
          "lon": 121.58989654,
          "lat": 32.66157971,
          "alt": 0.0,
          "raw": {
            "x": 649153.631,
            "y": 3616333.736,
            "z": 0.0
          }
        }
      ]
    },
    {
      "id": "1e4407f8cdea41fe9f66c782be61b513",
      "name": "风机中心点-1e4407f8cdea41fe9f66c782be61b513",
      "type": 0,
      "layer": "风机中心点",
      "points": [
        {
          "lon": 121.58404732,
          "lat": 32.65989374,
          "alt": 0.0,
          "raw": {
            "x": 648607.628,
            "y": 3616138.529,
            "z": 0.0
          }
        }
      ]
    },
    {
      "id": "41f97ec74ef74250935b0d7fe9f3fa62",
      "name": "风机中心点-41f97ec74ef74250935b0d7fe9f3fa62",
      "type": 0,
      "layer": "风机中心点",
      "points": [
        {
          "lon": 121.5431087,
          "lat": 32.64808411,
          "alt": 0.0,
          "raw": {
            "x": 644785.609,
            "y": 3614772.08,
            "z": 0.0
          }
        }
      ]
    },
    {
      "id": "9093c3109d06418cac3d389ec9da2978",
      "name": "风机中心点-9093c3109d06418cac3d389ec9da2978",
      "type": 0,
      "layer": "风机中心点",
      "points": [
        {
          "lon": 121.53726117,
          "lat": 32.6463959,
          "alt": 0.0,
          "raw": {
            "x": 644239.606,
            "y": 3614576.873,
            "z": 0.0
          }
        }
      ]
    },
    {
      "id": "8c85e95466a14a819deca40674dbca1d",
      "name": "风机中心点-8c85e95466a14a819deca40674dbca1d",
      "type": 0,
      "layer": "风机中心点",
      "points": [
        {
          "lon": 121.53141385,
          "lat": 32.64470741,
          "alt": 0.0,
          "raw": {
            "x": 643693.604,
            "y": 3614381.666,
            "z": 0.0
          }
        }
      ]
    },
    {
      "id": "9f13f4bc793a41438f2289ff27324faf",
      "name": "风机中心点-9f13f4bc793a41438f2289ff27324faf",
      "type": 0,
      "layer": "风机中心点",
      "points": [
        {
          "lon": 121.56065257,
          "lat": 32.65314716,
          "alt": 0.0,
          "raw": {
            "x": 646423.6169,
            "y": 3615357.713,
            "z": 0.0
          }
        }
      ]
    },
    {
      "id": "0025e5e36f904e6389aec0112e16b6f8",
      "name": "风机中心点-0025e5e36f904e6389aec0112e16b6f8",
      "type": 0,
      "layer": "风机中心点",
      "points": [
        {
          "lon": 121.55480439,
          "lat": 32.65145967,
          "alt": 0.0,
          "raw": {
            "x": 645877.613,
            "y": 3615162.492,
            "z": 0.0
          }
        }
      ]
    },
    {
      "id": "2f524aa10bc94189b4cdd0ff6a22639e",
      "name": "风机中心点-2f524aa10bc94189b4cdd0ff6a22639e",
      "type": 0,
      "layer": "风机中心点",
      "points": [
        {
          "lon": 121.54895645,
          "lat": 32.64977204,
          "alt": 0.0,
          "raw": {
            "x": 645331.612,
            "y": 3614967.287,
            "z": 0.0
          }
        }
      ]
    },
    {
      "id": "b4ae261cb4d845569854ceb7e8e8a32d",
      "name": "风机中心点-b4ae261cb4d845569854ceb7e8e8a32d",
      "type": 0,
      "layer": "风机中心点",
      "points": [
        {
          "lon": 121.6015956,
          "lat": 32.66495082,
          "alt": 0.0,
          "raw": {
            "x": 650245.6376,
            "y": 3616724.151,
            "z": 0.0
          }
        }
      ]
    },
    {
      "id": "7ca7b64454ef4158b43ac1e129dab3f0",
      "name": "风机中心点-7ca7b64454ef4158b43ac1e129dab3f0",
      "type": 0,
      "layer": "风机中心点",
      "points": [
        {
          "lon": 121.65425187,
          "lat": 32.6801069,
          "alt": 0.0,
          "raw": {
            "x": 655159.68,
            "y": 3618481.014,
            "z": 0.0
          }
        }
      ]
    },
    {
      "id": "599288d49dcd4c83bb02a4452e815f1f",
      "name": "风机中心点-599288d49dcd4c83bb02a4452e815f1f",
      "type": 0,
      "layer": "风机中心点",
      "points": [
        {
          "lon": 121.64840016,
          "lat": 32.67842401,
          "alt": 0.0,
          "raw": {
            "x": 654613.658,
            "y": 3618285.807,
            "z": 0.0
          }
        }
      ]
    },
    {
      "id": "34b4fa548f494b329503d44c69b21c84",
      "name": "风机中心点-34b4fa548f494b329503d44c69b21c84",
      "type": 0,
      "layer": "风机中心点",
      "points": [
        {
          "lon": 121.64254885,
          "lat": 32.67674085,
          "alt": 0.0,
          "raw": {
            "x": 654067.655,
            "y": 3618090.6,
            "z": 0.0
          }
        }
      ]
    },
    {
      "id": "596bdd9024154370980b5c66da853878",
      "name": "风机中心点-596bdd9024154370980b5c66da853878",
      "type": 0,
      "layer": "风机中心点",
      "points": [
        {
          "lon": 121.63520598,
          "lat": 32.69140294,
          "alt": 0.0,
          "raw": {
            "x": 653353.76,
            "y": 3619706.247,
            "z": 0.0
          }
        }
      ]
    },
    {
      "id": "fc89a88f2b674aebbdd34609cb429717",
      "name": "风机中心点-fc89a88f2b674aebbdd34609cb429717",
      "type": 0,
      "layer": "风机中心点",
      "points": [
        {
          "lon": 121.63978833,
          "lat": 32.69285397,
          "alt": 0.0,
          "raw": {
            "x": 653781.065,
            "y": 3619873.829,
            "z": 0.0
          }
        }
      ]
    },
    {
      "id": "e55b1600d7d941fcb339d8046bc2128a",
      "name": "风机中心点-e55b1600d7d941fcb339d8046bc2128a",
      "type": 0,
      "layer": "风机中心点",
      "points": [
        {
          "lon": 121.64437082,
          "lat": 32.69430483,
          "alt": 0.0,
          "raw": {
            "x": 654208.369,
            "y": 3620041.411,
            "z": 0.0
          }
        }
      ]
    },
    {
      "id": "59459abf1d0d435ba7d903a79392df34",
      "name": "风机中心点-59459abf1d0d435ba7d903a79392df34",
      "type": 0,
      "layer": "风机中心点",
      "points": [
        {
          "lon": 121.61914573,
          "lat": 32.67000537,
          "alt": 0.0,
          "raw": {
            "x": 651883.644,
            "y": 3617309.772,
            "z": 0.0
          }
        }
      ]
    },
    {
      "id": "0ce2ecafbcd44258a0661a64dd4c4b17",
      "name": "风机中心点-0ce2ecafbcd44258a0661a64dd4c4b17",
      "type": 0,
      "layer": "风机中心点",
      "points": [
        {
          "lon": 121.61329548,
          "lat": 32.6683208,
          "alt": 0.0,
          "raw": {
            "x": 651337.6425,
            "y": 3617114.565,
            "z": 0.0
          }
        }
      ]
    },
    {
      "id": "a6aab21f97c74aa0b1d6adecb7be99d6",
      "name": "风机中心点-a6aab21f97c74aa0b1d6adecb7be99d6",
      "type": 0,
      "layer": "风机中心点",
      "points": [
        {
          "lon": 121.60744543,
          "lat": 32.66663595,
          "alt": 0.0,
          "raw": {
            "x": 650791.639,
            "y": 3616919.358,
            "z": 0.0
          }
        }
      ]
    },
    {
      "id": "5844ca03f33649faa5b61f624ff239c2",
      "name": "风机中心点-5844ca03f33649faa5b61f624ff239c2",
      "type": 0,
      "layer": "风机中心点",
      "points": [
        {
          "lon": 121.63669775,
          "lat": 32.6750574,
          "alt": 0.0,
          "raw": {
            "x": 653521.6516,
            "y": 3617895.393,
            "z": 0.0
          }
        }
      ]
    },
    {
      "id": "6123ea0eca03446a9448a09e71341602",
      "name": "风机中心点-6123ea0eca03446a9448a09e71341602",
      "type": 0,
      "layer": "风机中心点",
      "points": [
        {
          "lon": 121.63084688,
          "lat": 32.67337367,
          "alt": 0.0,
          "raw": {
            "x": 652975.65,
            "y": 3617700.186,
            "z": 0.0
          }
        }
      ]
    },
    {
      "id": "7c102f4bda034a619702bafd472c357d",
      "name": "风机中心点-7c102f4bda034a619702bafd472c357d",
      "type": 0,
      "layer": "风机中心点",
      "points": [
        {
          "lon": 121.6249962,
          "lat": 32.67168966,
          "alt": 0.0,
          "raw": {
            "x": 652429.647,
            "y": 3617504.979,
            "z": 0.0
          }
        }
      ]
    },
    {
      "id": "cbd0d4188ce84325b55b4f037835b09b",
      "name": "风机中心点-cbd0d4188ce84325b55b4f037835b09b",
      "type": 0,
      "layer": "风机中心点",
      "points": [
        {
          "lon": 121.51611489,
          "lat": 32.65361559,
          "alt": 0.0,
          "raw": {
            "x": 642243.8419,
            "y": 3615349.112,
            "z": 0.0
          }
        }
      ]
    }
  ]
}
